sqltesty-0.2.0.dist-info/METADATA
sqltesty-0.2.0.dist-info/WHEEL
sqltesty-0.2.0.dist-info/entry_points.txt
sqltesty-0.2.0.dist-info/licenses/LICENSE
sqltesty/__init__.py
sqltesty/cli.py
sqltesty/helpers.py
sqltesty/output_formatter.py
sqltesty/runner.py
sqltesty-0.2.0.dist-info/RECORD
