Metadata-Version: 2.1
Name: sqltesty
Version: 0.2.0
Summary: Test SQL files using DuckDB and CSV fixtures
Author-Email: Pascal Stehling <pascal@stehl.ing>
License: MIT
Requires-Python: >=3.12
Requires-Dist: click>=8.1.7
Requires-Dist: duckdb>=0.10.0
Requires-Dist: pandas>=2.2.0
Requires-Dist: rich>=13.3.0
